README.rst
setup.py
stormbot_say/__init__.py
stormbot_say.egg-info/PKG-INFO
stormbot_say.egg-info/SOURCES.txt
stormbot_say.egg-info/dependency_links.txt
stormbot_say.egg-info/entry_points.txt
stormbot_say.egg-info/requires.txt
stormbot_say.egg-info/top_level.txt
tests/__init__.py
tests/test_say.py